sqlite_orm/__init__.py
sqlite_orm/database/__init__.py
sqlite_orm/database/database.py
sqlite_orm/database/query.py
sqlite_orm/exception/__init__.py
sqlite_orm/exception/exception_wrapper.py
sqlite_orm/field/__init__.py
sqlite_orm/field/base_field.py
sqlite_orm/field/boolean_field.py
sqlite_orm/field/integer_field.py
sqlite_orm/field/text_field.py
sqlite_orm/table/__init__.py
sqlite_orm/table/base_table.py
py_sqlite_orm_danidr-0.0.1.dist-info/METADATA
py_sqlite_orm_danidr-0.0.1.dist-info/WHEEL
py_sqlite_orm_danidr-0.0.1.dist-info/top_level.txt
py_sqlite_orm_danidr-0.0.1.dist-info/RECORD
