Metadata-Version: 2.1
Name: py-sqlite-orm-danidr
Version: 0.0.1
Summary: A Python object relational mapper for SQLite.
Home-page: https://github.com/DruzhininDV/sqlite-orm
Author: danydr
Author-email: ddv_2010@mail.ru
License: UNKNOWN
Platform: UNKNOWN
Classifier: Natural Language :: English
Classifier: Operating System :: OS Independent
Classifier: Programming Language :: Python :: 3
